zoocache/__init__.py
zoocache/_zoocache.abi3.so
zoocache/context.py
zoocache/core.py
zoocache-2026.1.20.dist-info/METADATA
zoocache-2026.1.20.dist-info/WHEEL
zoocache-2026.1.20.dist-info/RECORD
