Metadata-Version: 2.4
Name: zoocache
Version: 2026.1.20
Summary: Cache that invalidates when your data changes, not when a timer expires. Rust-powered semantic invalidation for Python.
Author-email: Alberto Daniel Badia <alberto_badia@enlacepatagonia.com>
License: MIT
Requires-Python: >=3.10
